[
  {
    "date": "2026-01-02",
    "open": 170.0,
    "high": 171.5,
    "low": 169.0,
    "close": 169.0,
    "volume": 795898,
    "turnover": 135336257,
    "change": -1.0
  },
  {
    "date": "2026-01-05",
    "open": 169.0,
    "high": 169.5,
    "low": 167.5,
    "close": 168.0,
    "volume": 1101546,
    "turnover": 185396381,
    "change": -1.0
  },
  {
    "date": "2026-01-06",
    "open": 169.0,
    "high": 171.0,
    "low": 168.5,
    "close": 169.5,
    "volume": 891015,
    "turnover": 151398717,
    "change": 1.5
  },
  {
    "date": "2026-01-07",
    "open": 170.0,
    "high": 172.5,
    "low": 169.5,
    "close": 171.5,
    "volume": 896207,
    "turnover": 153143712,
    "change": 2.0
  },
  {
    "date": "2026-01-08",
    "open": 171.5,
    "high": 173.5,
    "low": 170.0,
    "close": 172.0,
    "volume": 984359,
    "turnover": 168983972,
    "change": 0.5
  },
  {
    "date": "2026-01-09",
    "open": 173.5,
    "high": 174.5,
    "low": 170.5,
    "close": 174.0,
    "volume": 1869079,
    "turnover": 323943231,
    "change": 2.0
  },
  {
    "date": "2026-01-12",
    "open": 175.0,
    "high": 177.0,
    "low": 172.0,
    "close": 175.5,
    "volume": 2182794,
    "turnover": 382151986,
    "change": 1.5
  },
  {
    "date": "2026-01-13",
    "open": 181.0,
    "high": 188.0,
    "low": 179.0,
    "close": 180.0,
    "volume": 6226733,
    "turnover": 1134533975,
    "change": 4.5
  },
  {
    "date": "2026-01-14",
    "open": 182.5,
    "high": 198.0,
    "low": 182.5,
    "close": 198.0,
    "volume": 8561330,
    "turnover": 1648555708,
    "change": 18.0
  },
  {
    "date": "2026-01-15",
    "open": 205.5,
    "high": 206.0,
    "low": 193.5,
    "close": 197.0,
    "volume": 18639517,
    "turnover": 3702861763,
    "change": -1.0
  },
  {
    "date": "2026-01-16",
    "open": 200.0,
    "high": 204.5,
    "low": 195.0,
    "close": 197.0,
    "volume": 16524787,
    "turnover": 3298513741,
    "change": 0.0
  },
  {
    "date": "2026-01-19",
    "open": 199.5,
    "high": 210.5,
    "low": 195.0,
    "close": 207.0,
    "volume": 14620932,
    "turnover": 2993900800,
    "change": 10.0
  },
  {
    "date": "2026-01-20",
    "open": 205.5,
    "high": 221.5,
    "low": 204.0,
    "close": 218.0,
    "volume": 15191806,
    "turnover": 3252837191,
    "change": 11.0
  },
  {
    "date": "2026-01-21",
    "open": 217.0,
    "high": 225.0,
    "low": 215.0,
    "close": 215.5,
    "volume": 15604018,
    "turnover": 3426668809,
    "change": -2.5
  },
  {
    "date": "2026-01-22",
    "open": 223.0,
    "high": 237.0,
    "low": 219.0,
    "close": 237.0,
    "volume": 21096114,
    "turnover": 4900732457,
    "change": 21.5
  },
  {
    "date": "2026-01-23",
    "open": 239.0,
    "high": 246.0,
    "low": 224.0,
    "close": 226.0,
    "volume": 15637325,
    "turnover": 3634163292,
    "change": -11.0
  },
  {
    "date": "2026-01-26",
    "open": 229.0,
    "high": 234.0,
    "low": 221.5,
    "close": 228.0,
    "volume": 7248999,
    "turnover": 1646135168,
    "change": 2.0
  },
  {
    "date": "2026-01-27",
    "open": 231.0,
    "high": 231.5,
    "low": 220.0,
    "close": 224.0,
    "volume": 4567258,
    "turnover": 1020925216,
    "change": -4.0
  },
  {
    "date": "2026-01-28",
    "open": 226.5,
    "high": 246.0,
    "low": 222.0,
    "close": 246.0,
    "volume": 15529602,
    "turnover": 3675206682,
    "change": 22.0
  },
  {
    "date": "2026-01-29",
    "open": 247.0,
    "high": 252.0,
    "low": 233.5,
    "close": 241.5,
    "volume": 17310714,
    "turnover": 4183948464,
    "change": -4.5
  },
  {
    "date": "2026-01-30",
    "open": 240.0,
    "high": 243.0,
    "low": 226.0,
    "close": 229.0,
    "volume": 7355577,
    "turnover": 1700097274,
    "change": -12.5
  },
  {
    "date": "2026-02-02",
    "open": 224.5,
    "high": 226.0,
    "low": 212.5,
    "close": 216.0,
    "volume": 6545033,
    "turnover": 1423534451,
    "change": -13.0
  },
  {
    "date": "2026-02-03",
    "open": 223.5,
    "high": 225.5,
    "low": 213.0,
    "close": 216.5,
    "volume": 4964467,
    "turnover": 1089404127,
    "change": 0.5
  },
  {
    "date": "2026-02-04",
    "open": 214.0,
    "high": 223.5,
    "low": 214.0,
    "close": 221.5,
    "volume": 2796233,
    "turnover": 615501795,
    "change": 5.0
  },
  {
    "date": "2026-02-05",
    "open": 218.0,
    "high": 223.0,
    "low": 209.5,
    "close": 211.5,
    "volume": 3580117,
    "turnover": 765903028,
    "change": -10.0
  },
  {
    "date": "2026-02-06",
    "open": 207.5,
    "high": 208.5,
    "low": 200.5,
    "close": 201.0,
    "volume": 3341969,
    "turnover": 679093959,
    "change": -10.5
  },
  {
    "date": "2026-02-09",
    "open": 209.5,
    "high": 209.5,
    "low": 205.5,
    "close": 207.0,
    "volume": 1989919,
    "turnover": 412238928,
    "change": 6.0
  },
  {
    "date": "2026-02-10",
    "open": 210.0,
    "high": 213.5,
    "low": 203.0,
    "close": 206.5,
    "volume": 2694760,
    "turnover": 559981410,
    "change": -0.5
  }
]