[
  {
    "date": "2025-01-02",
    "open": 14.09,
    "high": 14.24,
    "low": 14.0,
    "close": 14.09,
    "volume": 1237355,
    "turnover": 18108750,
    "change": -0.1
  },
  {
    "date": "2025-01-03",
    "open": 14.14,
    "high": 14.19,
    "low": 13.95,
    "close": 14.0,
    "volume": 1317451,
    "turnover": 19207518,
    "change": -0.1
  },
  {
    "date": "2025-01-06",
    "open": 14.0,
    "high": 14.14,
    "low": 13.95,
    "close": 14.05,
    "volume": 925153,
    "turnover": 13532304,
    "change": 0.05
  },
  {
    "date": "2025-01-07",
    "open": 14.14,
    "high": 14.14,
    "low": 13.95,
    "close": 13.95,
    "volume": 1124566,
    "turnover": 16356394,
    "change": -0.1
  },
  {
    "date": "2025-01-08",
    "open": 13.95,
    "high": 14.05,
    "low": 13.85,
    "close": 13.95,
    "volume": 937034,
    "turnover": 13568647,
    "change": 0.0
  },
  {
    "date": "2025-01-09",
    "open": 13.95,
    "high": 14.0,
    "low": 13.71,
    "close": 13.76,
    "volume": 1754563,
    "turnover": 25217155,
    "change": -0.19
  },
  {
    "date": "2025-01-10",
    "open": 13.71,
    "high": 14.14,
    "low": 13.61,
    "close": 13.95,
    "volume": 2733333,
    "turnover": 39369073,
    "change": 0.19
  },
  {
    "date": "2025-01-13",
    "open": 14.09,
    "high": 14.09,
    "low": 13.76,
    "close": 13.95,
    "volume": 1915681,
    "turnover": 27687523,
    "change": 0.0
  },
  {
    "date": "2025-01-14",
    "open": 14.0,
    "high": 14.14,
    "low": 14.0,
    "close": 14.05,
    "volume": 957998,
    "turnover": 14011321,
    "change": 0.1
  },
  {
    "date": "2025-01-15",
    "open": 14.09,
    "high": 14.38,
    "low": 14.09,
    "close": 14.29,
    "volume": 3181803,
    "turnover": 47146890,
    "change": 0.24
  },
  {
    "date": "2025-01-16",
    "open": 14.33,
    "high": 14.43,
    "low": 14.24,
    "close": 14.33,
    "volume": 1831741,
    "turnover": 27295672,
    "change": 0.05
  },
  {
    "date": "2025-01-17",
    "open": 14.33,
    "high": 14.57,
    "low": 14.29,
    "close": 14.43,
    "volume": 2688846,
    "turnover": 40410385,
    "change": 0.1
  },
  {
    "date": "2025-01-20",
    "open": 14.48,
    "high": 14.57,
    "low": 14.33,
    "close": 14.53,
    "volume": 1763475,
    "turnover": 26508787,
    "change": 0.1
  },
  {
    "date": "2025-01-21",
    "open": 14.48,
    "high": 14.72,
    "low": 14.48,
    "close": 14.57,
    "volume": 970816,
    "turnover": 14693823,
    "change": 0.05
  },
  {
    "date": "2025-01-22",
    "open": 14.67,
    "high": 14.67,
    "low": 14.43,
    "close": 14.57,
    "volume": 1481061,
    "turnover": 22354260,
    "change": 0.0
  },
  {
    "date": "2025-02-03",
    "open": 14.38,
    "high": 14.57,
    "low": 14.29,
    "close": 14.38,
    "volume": 1310209,
    "turnover": 19635068,
    "change": -0.19
  },
  {
    "date": "2025-02-04",
    "open": 14.48,
    "high": 14.53,
    "low": 14.33,
    "close": 14.33,
    "volume": 1163575,
    "turnover": 17433480,
    "change": -0.05
  },
  {
    "date": "2025-02-05",
    "open": 14.43,
    "high": 14.48,
    "low": 14.29,
    "close": 14.29,
    "volume": 1309368,
    "turnover": 19503664,
    "change": -0.05
  },
  {
    "date": "2025-02-06",
    "open": 14.38,
    "high": 14.57,
    "low": 14.29,
    "close": 14.48,
    "volume": 1830112,
    "turnover": 27457787,
    "change": 0.19
  },
  {
    "date": "2025-02-07",
    "open": 14.48,
    "high": 14.48,
    "low": 14.33,
    "close": 14.38,
    "volume": 854246,
    "turnover": 12792467,
    "change": -0.1
  },
  {
    "date": "2025-02-10",
    "open": 14.33,
    "high": 14.62,
    "low": 14.33,
    "close": 14.53,
    "volume": 1875110,
    "turnover": 28249074,
    "change": 0.14
  },
  {
    "date": "2025-02-11",
    "open": 14.43,
    "high": 14.53,
    "low": 14.33,
    "close": 14.33,
    "volume": 1261818,
    "turnover": 18890250,
    "change": -0.19
  },
  {
    "date": "2025-02-12",
    "open": 14.33,
    "high": 14.43,
    "low": 14.29,
    "close": 14.33,
    "volume": 1142915,
    "turnover": 17044059,
    "change": 0.0
  },
  {
    "date": "2025-02-13",
    "open": 14.43,
    "high": 14.67,
    "low": 14.38,
    "close": 14.57,
    "volume": 3025222,
    "turnover": 45826921,
    "change": 0.24
  },
  {
    "date": "2025-02-14",
    "open": 14.53,
    "high": 14.62,
    "low": 14.48,
    "close": 14.57,
    "volume": 1107280,
    "turnover": 16751293,
    "change": 0.0
  },
  {
    "date": "2025-02-17",
    "open": 14.62,
    "high": 14.62,
    "low": 14.53,
    "close": 14.53,
    "volume": 1042448,
    "turnover": 15770994,
    "change": -0.05
  },
  {
    "date": "2025-02-18",
    "open": 14.53,
    "high": 14.57,
    "low": 14.43,
    "close": 14.48,
    "volume": 1018472,
    "turnover": 15324274,
    "change": -0.05
  },
  {
    "date": "2025-02-19",
    "open": 14.53,
    "high": 14.62,
    "low": 14.48,
    "close": 14.57,
    "volume": 1894406,
    "turnover": 28692211,
    "change": 0.1
  },
  {
    "date": "2025-02-20",
    "open": 14.62,
    "high": 14.77,
    "low": 14.57,
    "close": 14.67,
    "volume": 2489358,
    "turnover": 37981594,
    "change": 0.1
  },
  {
    "date": "2025-02-21",
    "open": 14.72,
    "high": 14.77,
    "low": 14.62,
    "close": 14.72,
    "volume": 1571861,
    "turnover": 24002269,
    "change": 0.05
  },
  {
    "date": "2025-02-24",
    "open": 14.67,
    "high": 14.82,
    "low": 14.67,
    "close": 14.67,
    "volume": 1286965,
    "turnover": 19703902,
    "change": -0.05
  },
  {
    "date": "2025-02-25",
    "open": 14.62,
    "high": 14.82,
    "low": 14.57,
    "close": 14.77,
    "volume": 2108563,
    "turnover": 32233836,
    "change": 0.1
  },
  {
    "date": "2025-02-26",
    "open": 14.77,
    "high": 14.82,
    "low": 14.72,
    "close": 14.72,
    "volume": 1388529,
    "turnover": 21273042,
    "change": -0.05
  },
  {
    "date": "2025-02-27",
    "open": 14.67,
    "high": 14.86,
    "low": 14.62,
    "close": 14.62,
    "volume": 1981905,
    "turnover": 30350613,
    "change": -0.1
  },
  {
    "date": "2025-03-03",
    "open": 14.57,
    "high": 14.62,
    "low": 14.53,
    "close": 14.62,
    "volume": 998063,
    "turnover": 15129793,
    "change": 0.0
  },
  {
    "date": "2025-03-04",
    "open": 14.53,
    "high": 14.67,
    "low": 14.38,
    "close": 14.67,
    "volume": 1763000,
    "turnover": 26600687,
    "change": 0.05
  },
  {
    "date": "2025-03-05",
    "open": 14.67,
    "high": 14.91,
    "low": 14.57,
    "close": 14.82,
    "volume": 2894501,
    "turnover": 44511026,
    "change": 0.14
  },
  {
    "date": "2025-03-06",
    "open": 14.82,
    "high": 14.91,
    "low": 14.67,
    "close": 14.72,
    "volume": 1302065,
    "turnover": 20024952,
    "change": -0.1
  },
  {
    "date": "2025-03-07",
    "open": 14.82,
    "high": 14.91,
    "low": 14.72,
    "close": 14.86,
    "volume": 2441937,
    "turnover": 37641655,
    "change": 0.14
  },
  {
    "date": "2025-03-10",
    "open": 14.91,
    "high": 14.96,
    "low": 14.82,
    "close": 14.91,
    "volume": 1566973,
    "turnover": 24282166,
    "change": 0.05
  },
  {
    "date": "2025-03-11",
    "open": 14.43,
    "high": 14.43,
    "low": 13.95,
    "close": 14.33,
    "volume": 6399549,
    "turnover": 94375267,
    "change": -0.58
  },
  {
    "date": "2025-03-12",
    "open": 14.33,
    "high": 14.33,
    "low": 14.19,
    "close": 14.24,
    "volume": 1704610,
    "turnover": 25243099,
    "change": -0.1
  },
  {
    "date": "2025-03-13",
    "open": 14.24,
    "high": 14.33,
    "low": 14.05,
    "close": 14.09,
    "volume": 2814042,
    "turnover": 41380423,
    "change": -0.14
  },
  {
    "date": "2025-03-14",
    "open": 14.05,
    "high": 14.24,
    "low": 14.05,
    "close": 14.19,
    "volume": 1369157,
    "turnover": 20118320,
    "change": 0.1
  },
  {
    "date": "2025-03-17",
    "open": 14.19,
    "high": 14.33,
    "low": 14.09,
    "close": 14.14,
    "volume": 1868319,
    "turnover": 27575740,
    "change": -0.05
  },
  {
    "date": "2025-03-18",
    "open": 14.19,
    "high": 14.24,
    "low": 14.14,
    "close": 14.19,
    "volume": 1709926,
    "turnover": 25224290,
    "change": 0.05
  },
  {
    "date": "2025-03-19",
    "open": 14.24,
    "high": 14.29,
    "low": 14.14,
    "close": 14.19,
    "volume": 841101,
    "turnover": 12411195,
    "change": 0.0
  },
  {
    "date": "2025-03-20",
    "open": 14.24,
    "high": 14.33,
    "low": 14.19,
    "close": 14.29,
    "volume": 1221321,
    "turnover": 18115788,
    "change": 0.1
  },
  {
    "date": "2025-03-21",
    "open": 14.24,
    "high": 14.29,
    "low": 14.14,
    "close": 14.14,
    "volume": 1285487,
    "turnover": 18960366,
    "change": -0.14
  },
  {
    "date": "2025-03-24",
    "open": 14.14,
    "high": 14.24,
    "low": 14.05,
    "close": 14.09,
    "volume": 1491962,
    "turnover": 21875985,
    "change": -0.05
  },
  {
    "date": "2025-03-25",
    "open": 14.19,
    "high": 14.19,
    "low": 13.95,
    "close": 14.0,
    "volume": 1924280,
    "turnover": 28055964,
    "change": -0.1
  },
  {
    "date": "2025-03-26",
    "open": 14.0,
    "high": 14.09,
    "low": 14.0,
    "close": 14.05,
    "volume": 578172,
    "turnover": 8444397,
    "change": 0.05
  },
  {
    "date": "2025-03-27",
    "open": 14.0,
    "high": 14.05,
    "low": 13.9,
    "close": 14.0,
    "volume": 1378236,
    "turnover": 20008684,
    "change": -0.05
  },
  {
    "date": "2025-03-28",
    "open": 13.95,
    "high": 13.95,
    "low": 13.66,
    "close": 13.66,
    "volume": 3824931,
    "turnover": 54671283,
    "change": -0.34
  },
  {
    "date": "2025-03-31",
    "open": 13.47,
    "high": 13.47,
    "low": 13.04,
    "close": 13.08,
    "volume": 5571978,
    "turnover": 76626214,
    "change": -0.58
  },
  {
    "date": "2025-04-01",
    "open": 13.13,
    "high": 13.47,
    "low": 13.13,
    "close": 13.32,
    "volume": 1405725,
    "turnover": 19478999,
    "change": 0.24
  },
  {
    "date": "2025-04-02",
    "open": 13.32,
    "high": 13.52,
    "low": 13.28,
    "close": 13.52,
    "volume": 867889,
    "turnover": 12092752,
    "change": 0.19
  },
  {
    "date": "2025-04-07",
    "open": 12.17,
    "high": 12.17,
    "low": 12.17,
    "close": 12.17,
    "volume": 1033016,
    "turnover": 13067408,
    "change": -1.35
  },
  {
    "date": "2025-04-08",
    "open": 11.16,
    "high": 11.64,
    "low": 11.06,
    "close": 11.45,
    "volume": 6822314,
    "turnover": 80035698,
    "change": -0.72
  },
  {
    "date": "2025-04-09",
    "open": 11.16,
    "high": 11.35,
    "low": 10.39,
    "close": 10.58,
    "volume": 6290080,
    "turnover": 70859223,
    "change": -0.87
  },
  {
    "date": "2025-04-10",
    "open": 11.59,
    "high": 11.64,
    "low": 11.45,
    "close": 11.64,
    "volume": 2099012,
    "turnover": 25319436,
    "change": 1.06
  },
  {
    "date": "2025-04-11",
    "open": 11.3,
    "high": 11.83,
    "low": 11.16,
    "close": 11.78,
    "volume": 3284086,
    "turnover": 39504202,
    "change": 0.14
  },
  {
    "date": "2025-04-14",
    "open": 11.83,
    "high": 12.03,
    "low": 11.74,
    "close": 11.78,
    "volume": 2512068,
    "turnover": 30995363,
    "change": 0.0
  },
  {
    "date": "2025-04-15",
    "open": 11.78,
    "high": 12.17,
    "low": 11.78,
    "close": 12.12,
    "volume": 1063931,
    "turnover": 13301361,
    "change": 0.34
  },
  {
    "date": "2025-04-16",
    "open": 12.03,
    "high": 12.03,
    "low": 11.78,
    "close": 11.83,
    "volume": 1108224,
    "turnover": 13703686,
    "change": -0.29
  },
  {
    "date": "2025-04-17",
    "open": 11.69,
    "high": 11.93,
    "low": 11.59,
    "close": 11.74,
    "volume": 729476,
    "turnover": 8910900,
    "change": -0.1
  },
  {
    "date": "2025-04-18",
    "open": 11.83,
    "high": 11.93,
    "low": 11.78,
    "close": 11.83,
    "volume": 756552,
    "turnover": 9321552,
    "change": 0.1
  },
  {
    "date": "2025-04-21",
    "open": 11.88,
    "high": 11.88,
    "low": 11.59,
    "close": 11.59,
    "volume": 700476,
    "turnover": 8536930,
    "change": -0.24
  },
  {
    "date": "2025-04-22",
    "open": 11.4,
    "high": 11.64,
    "low": 11.35,
    "close": 11.54,
    "volume": 826458,
    "turnover": 9890788,
    "change": -0.05
  },
  {
    "date": "2025-04-23",
    "open": 11.74,
    "high": 11.88,
    "low": 11.74,
    "close": 11.78,
    "volume": 846206,
    "turnover": 10381951,
    "change": 0.24
  },
  {
    "date": "2025-04-24",
    "open": 11.78,
    "high": 11.83,
    "low": 11.74,
    "close": 11.74,
    "volume": 360779,
    "turnover": 4410578,
    "change": -0.05
  },
  {
    "date": "2025-04-25",
    "open": 11.88,
    "high": 11.93,
    "low": 11.74,
    "close": 11.78,
    "volume": 848315,
    "turnover": 10416545,
    "change": 0.05
  },
  {
    "date": "2025-04-28",
    "open": 11.83,
    "high": 11.93,
    "low": 11.78,
    "close": 11.88,
    "volume": 670171,
    "turnover": 8258403,
    "change": 0.1
  },
  {
    "date": "2025-04-29",
    "open": 11.93,
    "high": 12.07,
    "low": 11.88,
    "close": 11.98,
    "volume": 798166,
    "turnover": 9947649,
    "change": 0.1
  },
  {
    "date": "2025-04-30",
    "open": 11.98,
    "high": 12.07,
    "low": 11.93,
    "close": 11.98,
    "volume": 1087660,
    "turnover": 13566334,
    "change": 0.0
  },
  {
    "date": "2025-05-02",
    "open": 12.03,
    "high": 12.51,
    "low": 11.98,
    "close": 12.36,
    "volume": 2114105,
    "turnover": 26970406,
    "change": 0.38
  },
  {
    "date": "2025-05-05",
    "open": 12.55,
    "high": 13.04,
    "low": 12.51,
    "close": 12.7,
    "volume": 4969298,
    "turnover": 66033216,
    "change": 0.34
  },
  {
    "date": "2025-05-06",
    "open": 12.75,
    "high": 12.84,
    "low": 12.55,
    "close": 12.6,
    "volume": 1689310,
    "turnover": 22236511,
    "change": -0.1
  },
  {
    "date": "2025-05-07",
    "open": 12.7,
    "high": 12.89,
    "low": 12.7,
    "close": 12.79,
    "volume": 2092426,
    "turnover": 27845911,
    "change": 0.19
  },
  {
    "date": "2025-05-08",
    "open": 12.79,
    "high": 12.84,
    "low": 12.65,
    "close": 12.65,
    "volume": 940577,
    "turnover": 12441157,
    "change": -0.14
  },
  {
    "date": "2025-05-09",
    "open": 12.65,
    "high": 12.75,
    "low": 12.55,
    "close": 12.65,
    "volume": 1131293,
    "turnover": 14886462,
    "change": 0.0
  },
  {
    "date": "2025-05-12",
    "open": 12.75,
    "high": 12.75,
    "low": 12.6,
    "close": 12.7,
    "volume": 1063018,
    "turnover": 14002304,
    "change": 0.05
  },
  {
    "date": "2025-05-13",
    "open": 12.79,
    "high": 12.79,
    "low": 12.55,
    "close": 12.55,
    "volume": 1440577,
    "turnover": 18921870,
    "change": -0.14
  },
  {
    "date": "2025-05-14",
    "open": 12.65,
    "high": 12.7,
    "low": 12.55,
    "close": 12.6,
    "volume": 1396990,
    "turnover": 18327299,
    "change": 0.05
  },
  {
    "date": "2025-05-15",
    "open": 12.6,
    "high": 12.65,
    "low": 12.46,
    "close": 12.51,
    "volume": 1225854,
    "turnover": 15976664,
    "change": -0.1
  },
  {
    "date": "2025-05-16",
    "open": 12.51,
    "high": 12.75,
    "low": 12.46,
    "close": 12.7,
    "volume": 1580842,
    "turnover": 20843575,
    "change": 0.19
  },
  {
    "date": "2025-05-19",
    "open": 12.79,
    "high": 12.79,
    "low": 12.6,
    "close": 12.75,
    "volume": 1127552,
    "turnover": 14913312,
    "change": 0.05
  },
  {
    "date": "2025-05-20",
    "open": 12.84,
    "high": 12.84,
    "low": 12.65,
    "close": 12.79,
    "volume": 967196,
    "turnover": 12798870,
    "change": 0.05
  },
  {
    "date": "2025-05-21",
    "open": 12.79,
    "high": 12.89,
    "low": 12.75,
    "close": 12.79,
    "volume": 1398635,
    "turnover": 18634840,
    "change": 0.0
  },
  {
    "date": "2025-05-22",
    "open": 12.65,
    "high": 12.79,
    "low": 12.65,
    "close": 12.7,
    "volume": 1405218,
    "turnover": 18568677,
    "change": -0.1
  },
  {
    "date": "2025-05-23",
    "open": 12.75,
    "high": 13.85,
    "low": 12.7,
    "close": 13.61,
    "volume": 15317323,
    "turnover": 213828716,
    "change": 0.91
  },
  {
    "date": "2025-05-26",
    "open": 13.71,
    "high": 13.85,
    "low": 13.23,
    "close": 13.37,
    "volume": 11420088,
    "turnover": 160830296,
    "change": -0.24
  },
  {
    "date": "2025-05-27",
    "open": 13.52,
    "high": 13.56,
    "low": 12.79,
    "close": 12.89,
    "volume": 6470787,
    "turnover": 88076301,
    "change": -0.48
  },
  {
    "date": "2025-05-28",
    "open": 13.23,
    "high": 13.42,
    "low": 12.65,
    "close": 12.79,
    "volume": 9484234,
    "turnover": 127350331,
    "change": -0.1
  },
  {
    "date": "2025-05-29",
    "open": 12.89,
    "high": 12.89,
    "low": 12.51,
    "close": 12.55,
    "volume": 3582966,
    "turnover": 46952600,
    "change": -0.24
  },
  {
    "date": "2025-06-02",
    "open": 12.41,
    "high": 12.46,
    "low": 12.12,
    "close": 12.12,
    "volume": 2662984,
    "turnover": 33813000,
    "change": -0.43
  },
  {
    "date": "2025-06-03",
    "open": 12.17,
    "high": 12.22,
    "low": 12.03,
    "close": 12.03,
    "volume": 1498185,
    "turnover": 18815789,
    "change": -0.1
  },
  {
    "date": "2025-06-04",
    "open": 12.22,
    "high": 12.31,
    "low": 12.12,
    "close": 12.17,
    "volume": 1390134,
    "turnover": 17620538,
    "change": 0.14
  },
  {
    "date": "2025-06-05",
    "open": 12.17,
    "high": 12.27,
    "low": 12.07,
    "close": 12.07,
    "volume": 1975432,
    "turnover": 24979844,
    "change": -0.1
  },
  {
    "date": "2025-06-06",
    "open": 12.17,
    "high": 12.27,
    "low": 12.12,
    "close": 12.12,
    "volume": 1333039,
    "turnover": 16852800,
    "change": 0.05
  },
  {
    "date": "2025-06-09",
    "open": 12.22,
    "high": 12.22,
    "low": 11.93,
    "close": 12.03,
    "volume": 2163853,
    "turnover": 27029774,
    "change": -0.1
  },
  {
    "date": "2025-06-10",
    "open": 12.03,
    "high": 12.27,
    "low": 12.03,
    "close": 12.07,
    "volume": 1903935,
    "turnover": 24015573,
    "change": 0.05
  },
  {
    "date": "2025-06-11",
    "open": 12.03,
    "high": 12.03,
    "low": 11.88,
    "close": 11.98,
    "volume": 2037892,
    "turnover": 25335480,
    "change": -0.1
  },
  {
    "date": "2025-06-12",
    "open": 12.03,
    "high": 12.03,
    "low": 11.83,
    "close": 11.83,
    "volume": 1594410,
    "turnover": 19718494,
    "change": -0.14
  },
  {
    "date": "2025-06-13",
    "open": 11.78,
    "high": 11.88,
    "low": 11.64,
    "close": 11.64,
    "volume": 3410068,
    "turnover": 41622984,
    "change": -0.19
  },
  {
    "date": "2025-06-16",
    "open": 11.64,
    "high": 11.74,
    "low": 11.59,
    "close": 11.64,
    "volume": 976126,
    "turnover": 11820682,
    "change": 0.0
  },
  {
    "date": "2025-06-17",
    "open": 11.64,
    "high": 11.78,
    "low": 11.59,
    "close": 11.78,
    "volume": 1201257,
    "turnover": 14602882,
    "change": 0.14
  },
  {
    "date": "2025-06-18",
    "open": 11.74,
    "high": 11.93,
    "low": 11.69,
    "close": 11.83,
    "volume": 2515927,
    "turnover": 30901545,
    "change": 0.05
  },
  {
    "date": "2025-06-19",
    "open": 11.78,
    "high": 11.83,
    "low": 11.64,
    "close": 11.64,
    "volume": 1926244,
    "turnover": 23404789,
    "change": -0.19
  },
  {
    "date": "2025-06-20",
    "open": 11.64,
    "high": 11.64,
    "low": 11.45,
    "close": 11.45,
    "volume": 13844449,
    "turnover": 164932058,
    "change": -0.19
  },
  {
    "date": "2025-06-23",
    "open": 11.35,
    "high": 11.45,
    "low": 11.21,
    "close": 11.35,
    "volume": 2868349,
    "turnover": 33773141,
    "change": -0.1
  },
  {
    "date": "2025-06-24",
    "open": 11.5,
    "high": 11.69,
    "low": 11.45,
    "close": 11.64,
    "volume": 2160337,
    "turnover": 26052295,
    "change": 0.29
  },
  {
    "date": "2025-06-25",
    "open": 11.69,
    "high": 11.78,
    "low": 11.64,
    "close": 11.69,
    "volume": 1176902,
    "turnover": 14297929,
    "change": 0.05
  },
  {
    "date": "2025-06-26",
    "open": 11.74,
    "high": 11.93,
    "low": 11.74,
    "close": 11.83,
    "volume": 2713835,
    "turnover": 33398009,
    "change": 0.14
  },
  {
    "date": "2025-06-27",
    "open": 11.83,
    "high": 12.12,
    "low": 11.83,
    "close": 11.98,
    "volume": 3184066,
    "turnover": 39671577,
    "change": 0.14
  },
  {
    "date": "2025-06-30",
    "open": 11.98,
    "high": 12.03,
    "low": 11.69,
    "close": 11.69,
    "volume": 2064327,
    "turnover": 25314901,
    "change": -0.29
  },
  {
    "date": "2025-07-01",
    "open": 11.74,
    "high": 11.98,
    "low": 11.74,
    "close": 11.83,
    "volume": 2278253,
    "turnover": 28112558,
    "change": 0.14
  },
  {
    "date": "2025-07-02",
    "open": 11.88,
    "high": 11.88,
    "low": 11.78,
    "close": 11.78,
    "volume": 1038283,
    "turnover": 12753608,
    "change": -0.05
  },
  {
    "date": "2025-07-03",
    "open": 11.78,
    "high": 11.98,
    "low": 11.78,
    "close": 11.88,
    "volume": 3123255,
    "turnover": 38573919,
    "change": 0.1
  },
  {
    "date": "2025-07-04",
    "open": 11.88,
    "high": 11.93,
    "low": 11.64,
    "close": 11.74,
    "volume": 2115739,
    "turnover": 25859283,
    "change": -0.14
  },
  {
    "date": "2025-07-07",
    "open": 11.74,
    "high": 11.93,
    "low": 11.64,
    "close": 11.93,
    "volume": 1496337,
    "turnover": 18442608,
    "change": 0.19
  },
  {
    "date": "2025-07-08",
    "open": 11.88,
    "high": 11.93,
    "low": 11.74,
    "close": 11.78,
    "volume": 1003677,
    "turnover": 12294147,
    "change": -0.14
  },
  {
    "date": "2025-07-09",
    "open": 11.74,
    "high": 11.78,
    "low": 11.69,
    "close": 11.69,
    "volume": 529181,
    "turnover": 6453328,
    "change": -0.1
  },
  {
    "date": "2025-07-10",
    "open": 11.69,
    "high": 11.74,
    "low": 11.59,
    "close": 11.69,
    "volume": 1190388,
    "turnover": 14399273,
    "change": 0.0
  },
  {
    "date": "2025-07-11",
    "open": 11.69,
    "high": 11.88,
    "low": 11.59,
    "close": 11.83,
    "volume": 1353367,
    "turnover": 16582264,
    "change": 0.14
  },
  {
    "date": "2025-07-14",
    "open": 11.83,
    "high": 11.93,
    "low": 11.78,
    "close": 11.83,
    "volume": 656798,
    "turnover": 8086312,
    "change": 0.0
  },
  {
    "date": "2025-07-15",
    "open": 11.78,
    "high": 11.98,
    "low": 11.78,
    "close": 11.83,
    "volume": 904147,
    "turnover": 11146669,
    "change": 0.0
  },
  {
    "date": "2025-07-16",
    "open": 11.78,
    "high": 11.93,
    "low": 11.78,
    "close": 11.88,
    "volume": 1072919,
    "turnover": 13247259,
    "change": 0.05
  },
  {
    "date": "2025-07-17",
    "open": 11.93,
    "high": 12.07,
    "low": 11.93,
    "close": 12.03,
    "volume": 1138623,
    "turnover": 14217966,
    "change": 0.14
  },
  {
    "date": "2025-07-18",
    "open": 12.12,
    "high": 12.12,
    "low": 12.03,
    "close": 12.12,
    "volume": 856919,
    "turnover": 10749532,
    "change": 0.1
  },
  {
    "date": "2025-07-21",
    "open": 12.12,
    "high": 12.27,
    "low": 12.07,
    "close": 12.17,
    "volume": 1531484,
    "turnover": 19400361,
    "change": 0.05
  },
  {
    "date": "2025-07-22",
    "open": 12.17,
    "high": 12.22,
    "low": 11.93,
    "close": 11.93,
    "volume": 1296334,
    "turnover": 16254126,
    "change": -0.24
  },
  {
    "date": "2025-07-23",
    "open": 12.03,
    "high": 12.31,
    "low": 11.98,
    "close": 12.31,
    "volume": 2176737,
    "turnover": 27628476,
    "change": 0.38
  },
  {
    "date": "2025-07-24",
    "open": 12.22,
    "high": 12.31,
    "low": 12.07,
    "close": 12.17,
    "volume": 874775,
    "turnover": 11067950,
    "change": -0.14
  },
  {
    "date": "2025-07-25",
    "open": 12.12,
    "high": 12.27,
    "low": 12.12,
    "close": 12.17,
    "volume": 830683,
    "turnover": 10549817,
    "change": 0.0
  },
  {
    "date": "2025-07-28",
    "open": 12.17,
    "high": 12.41,
    "low": 12.17,
    "close": 12.36,
    "volume": 1133044,
    "turnover": 14490863,
    "change": 0.19
  },
  {
    "date": "2025-07-29",
    "open": 12.41,
    "high": 12.46,
    "low": 12.22,
    "close": 12.27,
    "volume": 1021490,
    "turnover": 13092859,
    "change": -0.1
  },
  {
    "date": "2025-07-30",
    "open": 12.27,
    "high": 12.55,
    "low": 12.27,
    "close": 12.51,
    "volume": 2741435,
    "turnover": 35550036,
    "change": 0.24
  },
  {
    "date": "2025-07-31",
    "open": 12.41,
    "high": 12.55,
    "low": 12.36,
    "close": 12.41,
    "volume": 1798726,
    "turnover": 23295266,
    "change": -0.1
  },
  {
    "date": "2025-08-01",
    "open": 12.41,
    "high": 12.6,
    "low": 12.27,
    "close": 12.51,
    "volume": 2701561,
    "turnover": 35020064,
    "change": 0.1
  },
  {
    "date": "2025-08-04",
    "open": 12.36,
    "high": 12.41,
    "low": 12.12,
    "close": 12.31,
    "volume": 1635948,
    "turnover": 20898603,
    "change": -0.19
  },
  {
    "date": "2025-08-05",
    "open": 12.27,
    "high": 12.36,
    "low": 11.93,
    "close": 12.03,
    "volume": 4675721,
    "turnover": 58451791,
    "change": -0.29
  },
  {
    "date": "2025-08-06",
    "open": 12.03,
    "high": 12.17,
    "low": 12.03,
    "close": 12.12,
    "volume": 1900624,
    "turnover": 23923614,
    "change": 0.1
  },
  {
    "date": "2025-08-07",
    "open": 12.12,
    "high": 12.27,
    "low": 12.12,
    "close": 12.22,
    "volume": 2219147,
    "turnover": 28144474,
    "change": 0.1
  },
  {
    "date": "2025-08-08",
    "open": 12.22,
    "high": 12.36,
    "low": 12.22,
    "close": 12.22,
    "volume": 1100104,
    "turnover": 14034978,
    "change": 0.0
  },
  {
    "date": "2025-08-11",
    "open": 12.17,
    "high": 12.22,
    "low": 11.93,
    "close": 12.03,
    "volume": 2573639,
    "turnover": 32264486,
    "change": -0.19
  },
  {
    "date": "2025-08-12",
    "open": 11.93,
    "high": 12.17,
    "low": 11.93,
    "close": 12.07,
    "volume": 1613044,
    "turnover": 20189472,
    "change": 0.05
  },
  {
    "date": "2025-08-13",
    "open": 12.46,
    "high": 13.28,
    "low": 12.46,
    "close": 13.28,
    "volume": 13888178,
    "turnover": 188619710,
    "change": 1.2
  },
  {
    "date": "2025-08-14",
    "open": 13.9,
    "high": 14.33,
    "low": 13.56,
    "close": 14.09,
    "volume": 47554785,
    "turnover": 692940968,
    "change": 0.82
  },
  {
    "date": "2025-08-15",
    "open": 13.95,
    "high": 15.49,
    "low": 13.47,
    "close": 15.49,
    "volume": 45043905,
    "turnover": 687148092,
    "change": 1.39
  },
  {
    "date": "2025-08-18",
    "open": 15.97,
    "high": 17.03,
    "low": 15.87,
    "close": 17.03,
    "volume": 105623992,
    "turnover": 1828111721,
    "change": 1.54
  },
  {
    "date": "2025-08-19",
    "open": 17.61,
    "high": 18.47,
    "low": 16.98,
    "close": 17.12,
    "volume": 129974732,
    "turnover": 2409608697,
    "change": 0.1
  },
  {
    "date": "2025-08-20",
    "open": 16.88,
    "high": 16.88,
    "low": 15.58,
    "close": 15.83,
    "volume": 60229591,
    "turnover": 1001561683,
    "change": -1.3
  },
  {
    "date": "2025-08-21",
    "open": 16.11,
    "high": 16.74,
    "low": 15.92,
    "close": 15.97,
    "volume": 37247268,
    "turnover": 629970310,
    "change": 0.14
  },
  {
    "date": "2025-08-22",
    "open": 16.16,
    "high": 16.35,
    "low": 15.01,
    "close": 15.15,
    "volume": 40314904,
    "turnover": 648615394,
    "change": -0.82
  },
  {
    "date": "2025-08-25",
    "open": 15.39,
    "high": 15.44,
    "low": 15.06,
    "close": 15.2,
    "volume": 23300371,
    "turnover": 368015342,
    "change": 0.05
  },
  {
    "date": "2025-08-26",
    "open": 15.5,
    "high": 15.75,
    "low": 15.05,
    "close": 15.05,
    "volume": 21295817,
    "turnover": 327168904,
    "change": -0.15
  },
  {
    "date": "2025-08-27",
    "open": 15.15,
    "high": 15.25,
    "low": 14.9,
    "close": 14.9,
    "volume": 16020246,
    "turnover": 240829698,
    "change": -0.15
  },
  {
    "date": "2025-08-28",
    "open": 15.1,
    "high": 15.8,
    "low": 15.1,
    "close": 15.25,
    "volume": 25590205,
    "turnover": 395615338,
    "change": 0.35
  },
  {
    "date": "2025-08-29",
    "open": 15.35,
    "high": 15.5,
    "low": 14.85,
    "close": 14.9,
    "volume": 24054437,
    "turnover": 364223883,
    "change": -0.35
  },
  {
    "date": "2025-09-01",
    "open": 14.9,
    "high": 15.05,
    "low": 14.7,
    "close": 14.75,
    "volume": 10404184,
    "turnover": 154380566,
    "change": -0.15
  },
  {
    "date": "2025-09-02",
    "open": 14.95,
    "high": 15.2,
    "low": 14.3,
    "close": 14.4,
    "volume": 13297856,
    "turnover": 195203295,
    "change": -0.35
  },
  {
    "date": "2025-09-03",
    "open": 14.35,
    "high": 14.9,
    "low": 14.25,
    "close": 14.75,
    "volume": 8875610,
    "turnover": 129511155,
    "change": 0.35
  },
  {
    "date": "2025-09-04",
    "open": 14.85,
    "high": 14.9,
    "low": 14.45,
    "close": 14.6,
    "volume": 9330375,
    "turnover": 136291574,
    "change": -0.15
  },
  {
    "date": "2025-09-05",
    "open": 14.6,
    "high": 14.75,
    "low": 14.3,
    "close": 14.5,
    "volume": 6694957,
    "turnover": 96785524,
    "change": -0.1
  },
  {
    "date": "2025-09-08",
    "open": 14.65,
    "high": 14.7,
    "low": 14.35,
    "close": 14.5,
    "volume": 5166401,
    "turnover": 74942771,
    "change": 0.0
  },
  {
    "date": "2025-09-09",
    "open": 14.55,
    "high": 14.75,
    "low": 14.45,
    "close": 14.5,
    "volume": 7220801,
    "turnover": 105309535,
    "change": 0.0
  },
  {
    "date": "2025-09-10",
    "open": 14.55,
    "high": 14.65,
    "low": 14.35,
    "close": 14.5,
    "volume": 6333822,
    "turnover": 91926807,
    "change": 0.0
  },
  {
    "date": "2025-09-11",
    "open": 14.65,
    "high": 14.65,
    "low": 14.1,
    "close": 14.1,
    "volume": 10231846,
    "turnover": 146111064,
    "change": -0.4
  },
  {
    "date": "2025-09-12",
    "open": 14.25,
    "high": 14.5,
    "low": 14.2,
    "close": 14.35,
    "volume": 5565675,
    "turnover": 80013168,
    "change": 0.25
  },
  {
    "date": "2025-09-15",
    "open": 14.5,
    "high": 14.65,
    "low": 14.25,
    "close": 14.3,
    "volume": 5691243,
    "turnover": 82106038,
    "change": -0.05
  },
  {
    "date": "2025-09-16",
    "open": 14.35,
    "high": 14.35,
    "low": 14.15,
    "close": 14.2,
    "volume": 4256547,
    "turnover": 60451490,
    "change": -0.1
  },
  {
    "date": "2025-09-17",
    "open": 14.25,
    "high": 14.55,
    "low": 14.25,
    "close": 14.35,
    "volume": 6659191,
    "turnover": 95926101,
    "change": 0.15
  },
  {
    "date": "2025-09-18",
    "open": 14.5,
    "high": 14.55,
    "low": 14.35,
    "close": 14.35,
    "volume": 3919906,
    "turnover": 56456147,
    "change": 0.0
  },
  {
    "date": "2025-09-19",
    "open": 14.4,
    "high": 14.55,
    "low": 14.25,
    "close": 14.3,
    "volume": 5889902,
    "turnover": 84685236,
    "change": -0.05
  },
  {
    "date": "2025-09-22",
    "open": 14.4,
    "high": 14.55,
    "low": 14.25,
    "close": 14.4,
    "volume": 5530211,
    "turnover": 79674828,
    "change": 0.1
  },
  {
    "date": "2025-09-23",
    "open": 14.55,
    "high": 14.55,
    "low": 14.15,
    "close": 14.2,
    "volume": 6013371,
    "turnover": 85767394,
    "change": -0.2
  },
  {
    "date": "2025-09-24",
    "open": 14.25,
    "high": 14.45,
    "low": 14.1,
    "close": 14.1,
    "volume": 4363058,
    "turnover": 61919953,
    "change": -0.1
  },
  {
    "date": "2025-09-25",
    "open": 14.2,
    "high": 14.55,
    "low": 14.2,
    "close": 14.3,
    "volume": 6352023,
    "turnover": 91624205,
    "change": 0.2
  },
  {
    "date": "2025-09-26",
    "open": 14.4,
    "high": 14.4,
    "low": 14.1,
    "close": 14.15,
    "volume": 5184198,
    "turnover": 73558306,
    "change": -0.15
  },
  {
    "date": "2025-09-30",
    "open": 14.3,
    "high": 14.3,
    "low": 14.15,
    "close": 14.15,
    "volume": 2883955,
    "turnover": 40983534,
    "change": 0.0
  },
  {
    "date": "2025-10-01",
    "open": 14.2,
    "high": 14.55,
    "low": 14.2,
    "close": 14.3,
    "volume": 5570956,
    "turnover": 80092984,
    "change": 0.15
  },
  {
    "date": "2025-10-02",
    "open": 14.45,
    "high": 14.6,
    "low": 14.25,
    "close": 14.35,
    "volume": 5410845,
    "turnover": 77923955,
    "change": 0.05
  },
  {
    "date": "2025-10-03",
    "open": 14.35,
    "high": 14.4,
    "low": 14.2,
    "close": 14.2,
    "volume": 2700818,
    "turnover": 38460816,
    "change": -0.15
  },
  {
    "date": "2025-10-07",
    "open": 14.2,
    "high": 14.4,
    "low": 14.1,
    "close": 14.2,
    "volume": 3995279,
    "turnover": 56969056,
    "change": 0.0
  },
  {
    "date": "2025-10-08",
    "open": 14.2,
    "high": 14.3,
    "low": 14.1,
    "close": 14.15,
    "volume": 3138081,
    "turnover": 44480504,
    "change": -0.05
  },
  {
    "date": "2025-10-09",
    "open": 14.2,
    "high": 14.35,
    "low": 14.1,
    "close": 14.25,
    "volume": 4001033,
    "turnover": 57052954,
    "change": 0.1
  },
  {
    "date": "2025-10-13",
    "open": 13.6,
    "high": 13.85,
    "low": 13.45,
    "close": 13.8,
    "volume": 7620046,
    "turnover": 104103889,
    "change": -0.45
  },
  {
    "date": "2025-10-14",
    "open": 13.85,
    "high": 14.0,
    "low": 13.35,
    "close": 13.35,
    "volume": 8241014,
    "turnover": 112201548,
    "change": -0.45
  },
  {
    "date": "2025-10-15",
    "open": 13.45,
    "high": 13.55,
    "low": 13.15,
    "close": 13.2,
    "volume": 5471915,
    "turnover": 72716765,
    "change": -0.15
  },
  {
    "date": "2025-10-16",
    "open": 13.2,
    "high": 13.4,
    "low": 13.2,
    "close": 13.3,
    "volume": 3504185,
    "turnover": 46571536,
    "change": 0.1
  },
  {
    "date": "2025-10-17",
    "open": 13.25,
    "high": 13.7,
    "low": 13.25,
    "close": 13.3,
    "volume": 3841293,
    "turnover": 51637850,
    "change": 0.0
  },
  {
    "date": "2025-10-20",
    "open": 13.35,
    "high": 13.5,
    "low": 13.25,
    "close": 13.35,
    "volume": 2234083,
    "turnover": 29837755,
    "change": 0.05
  },
  {
    "date": "2025-10-21",
    "open": 13.35,
    "high": 13.5,
    "low": 13.35,
    "close": 13.35,
    "volume": 2405270,
    "turnover": 32271748,
    "change": 0.0
  },
  {
    "date": "2025-10-22",
    "open": 13.35,
    "high": 13.7,
    "low": 13.35,
    "close": 13.55,
    "volume": 3747322,
    "turnover": 50795151,
    "change": 0.2
  },
  {
    "date": "2025-10-23",
    "open": 13.7,
    "high": 13.8,
    "low": 13.45,
    "close": 13.7,
    "volume": 3664332,
    "turnover": 50146035,
    "change": 0.15
  },
  {
    "date": "2025-10-27",
    "open": 13.9,
    "high": 13.95,
    "low": 13.7,
    "close": 13.85,
    "volume": 3757047,
    "turnover": 52041677,
    "change": 0.15
  },
  {
    "date": "2025-10-28",
    "open": 13.9,
    "high": 14.35,
    "low": 13.7,
    "close": 14.3,
    "volume": 8601757,
    "turnover": 121018848,
    "change": 0.45
  },
  {
    "date": "2025-10-29",
    "open": 14.6,
    "high": 14.7,
    "low": 13.9,
    "close": 13.9,
    "volume": 14452956,
    "turnover": 205145641,
    "change": -0.4
  },
  {
    "date": "2025-10-30",
    "open": 13.95,
    "high": 14.05,
    "low": 13.55,
    "close": 13.6,
    "volume": 6800358,
    "turnover": 93225691,
    "change": -0.3
  },
  {
    "date": "2025-10-31",
    "open": 13.7,
    "high": 13.7,
    "low": 13.35,
    "close": 13.35,
    "volume": 3534084,
    "turnover": 47583570,
    "change": -0.25
  },
  {
    "date": "2025-11-03",
    "open": 13.35,
    "high": 13.45,
    "low": 13.25,
    "close": 13.3,
    "volume": 2224157,
    "turnover": 29648023,
    "change": -0.05
  },
  {
    "date": "2025-11-04",
    "open": 13.3,
    "high": 13.45,
    "low": 13.15,
    "close": 13.15,
    "volume": 2334322,
    "turnover": 30934523,
    "change": -0.15
  },
  {
    "date": "2025-11-05",
    "open": 13.1,
    "high": 13.4,
    "low": 12.95,
    "close": 13.3,
    "volume": 5185063,
    "turnover": 68277790,
    "change": 0.15
  },
  {
    "date": "2025-11-06",
    "open": 13.4,
    "high": 13.8,
    "low": 13.4,
    "close": 13.8,
    "volume": 4433512,
    "turnover": 60516845,
    "change": 0.5
  },
  {
    "date": "2025-11-07",
    "open": 13.7,
    "high": 13.9,
    "low": 13.65,
    "close": 13.7,
    "volume": 2211809,
    "turnover": 30432735,
    "change": -0.1
  },
  {
    "date": "2025-11-10",
    "open": 13.7,
    "high": 13.95,
    "low": 13.55,
    "close": 13.9,
    "volume": 2312730,
    "turnover": 31864798,
    "change": 0.2
  },
  {
    "date": "2025-11-11",
    "open": 14.4,
    "high": 14.55,
    "low": 14.15,
    "close": 14.2,
    "volume": 10383086,
    "turnover": 149251267,
    "change": 0.3
  },
  {
    "date": "2025-11-12",
    "open": 14.3,
    "high": 15.15,
    "low": 14.3,
    "close": 15.0,
    "volume": 19086952,
    "turnover": 282768562,
    "change": 0.8
  },
  {
    "date": "2025-11-13",
    "open": 15.05,
    "high": 15.4,
    "low": 14.9,
    "close": 15.3,
    "volume": 14199014,
    "turnover": 215636930,
    "change": 0.3
  },
  {
    "date": "2025-11-14",
    "open": 15.0,
    "high": 15.75,
    "low": 15.0,
    "close": 15.4,
    "volume": 15343435,
    "turnover": 236854847,
    "change": 0.1
  },
  {
    "date": "2025-11-17",
    "open": 15.8,
    "high": 16.45,
    "low": 15.7,
    "close": 15.8,
    "volume": 22988036,
    "turnover": 367204836,
    "change": 0.4
  },
  {
    "date": "2025-11-18",
    "open": 15.7,
    "high": 16.1,
    "low": 15.6,
    "close": 15.95,
    "volume": 12872343,
    "turnover": 204244414,
    "change": 0.15
  },
  {
    "date": "2025-11-19",
    "open": 15.9,
    "high": 16.05,
    "low": 15.55,
    "close": 15.65,
    "volume": 10600027,
    "turnover": 167335434,
    "change": -0.3
  },
  {
    "date": "2025-11-20",
    "open": 15.9,
    "high": 16.1,
    "low": 15.65,
    "close": 15.75,
    "volume": 7507171,
    "turnover": 118811458,
    "change": 0.1
  },
  {
    "date": "2025-11-21",
    "open": 15.6,
    "high": 15.7,
    "low": 15.15,
    "close": 15.35,
    "volume": 8871367,
    "turnover": 136757323,
    "change": -0.4
  },
  {
    "date": "2025-11-24",
    "open": 15.5,
    "high": 15.55,
    "low": 15.2,
    "close": 15.4,
    "volume": 6386301,
    "turnover": 98239880,
    "change": 0.05
  },
  {
    "date": "2025-11-25",
    "open": 15.5,
    "high": 15.6,
    "low": 15.15,
    "close": 15.3,
    "volume": 4219097,
    "turnover": 64513731,
    "change": -0.1
  },
  {
    "date": "2025-11-26",
    "open": 15.35,
    "high": 15.9,
    "low": 15.35,
    "close": 15.8,
    "volume": 7607553,
    "turnover": 119624206,
    "change": 0.5
  },
  {
    "date": "2025-11-27",
    "open": 15.95,
    "high": 16.1,
    "low": 15.7,
    "close": 15.85,
    "volume": 5189680,
    "turnover": 82305754,
    "change": 0.05
  },
  {
    "date": "2025-11-28",
    "open": 15.95,
    "high": 16.25,
    "low": 15.7,
    "close": 16.2,
    "volume": 13274997,
    "turnover": 213034865,
    "change": 0.35
  },
  {
    "date": "2025-12-01",
    "open": 16.2,
    "high": 16.4,
    "low": 16.0,
    "close": 16.05,
    "volume": 10249986,
    "turnover": 165928906,
    "change": -0.15
  },
  {
    "date": "2025-12-02",
    "open": 16.0,
    "high": 16.35,
    "low": 15.65,
    "close": 15.7,
    "volume": 10222437,
    "turnover": 162939908,
    "change": -0.35
  },
  {
    "date": "2025-12-03",
    "open": 15.7,
    "high": 15.95,
    "low": 15.5,
    "close": 15.7,
    "volume": 6628575,
    "turnover": 104038253,
    "change": 0.0
  },
  {
    "date": "2025-12-04",
    "open": 15.8,
    "high": 15.8,
    "low": 15.35,
    "close": 15.45,
    "volume": 4655869,
    "turnover": 72238079,
    "change": -0.25
  },
  {
    "date": "2025-12-05",
    "open": 15.4,
    "high": 15.45,
    "low": 15.05,
    "close": 15.1,
    "volume": 6402189,
    "turnover": 97076718,
    "change": -0.35
  },
  {
    "date": "2025-12-08",
    "open": 15.1,
    "high": 15.1,
    "low": 14.85,
    "close": 15.1,
    "volume": 4161431,
    "turnover": 62322783,
    "change": 0.0
  },
  {
    "date": "2025-12-09",
    "open": 15.05,
    "high": 15.3,
    "low": 14.9,
    "close": 15.2,
    "volume": 2309655,
    "turnover": 34972705,
    "change": 0.1
  },
  {
    "date": "2025-12-10",
    "open": 15.1,
    "high": 15.25,
    "low": 14.7,
    "close": 14.7,
    "volume": 6419663,
    "turnover": 95491309,
    "change": -0.5
  },
  {
    "date": "2025-12-11",
    "open": 14.7,
    "high": 14.95,
    "low": 14.7,
    "close": 14.75,
    "volume": 2562208,
    "turnover": 37951894,
    "change": 0.05
  },
  {
    "date": "2025-12-12",
    "open": 14.9,
    "high": 15.1,
    "low": 14.8,
    "close": 14.85,
    "volume": 2801189,
    "turnover": 41823434,
    "change": 0.1
  },
  {
    "date": "2025-12-15",
    "open": 14.8,
    "high": 15.05,
    "low": 14.75,
    "close": 14.95,
    "volume": 2224728,
    "turnover": 33267316,
    "change": 0.1
  },
  {
    "date": "2025-12-16",
    "open": 14.85,
    "high": 15.0,
    "low": 14.75,
    "close": 14.95,
    "volume": 3269722,
    "turnover": 48573798,
    "change": 0.0
  },
  {
    "date": "2025-12-17",
    "open": 15.0,
    "high": 15.35,
    "low": 15.0,
    "close": 15.05,
    "volume": 4724701,
    "turnover": 71678370,
    "change": 0.1
  },
  {
    "date": "2025-12-18",
    "open": 15.1,
    "high": 15.4,
    "low": 15.1,
    "close": 15.3,
    "volume": 3730519,
    "turnover": 57000448,
    "change": 0.25
  },
  {
    "date": "2025-12-19",
    "open": 15.25,
    "high": 15.65,
    "low": 15.2,
    "close": 15.4,
    "volume": 4755902,
    "turnover": 73452294,
    "change": 0.1
  },
  {
    "date": "2025-12-22",
    "open": 15.55,
    "high": 15.85,
    "low": 15.45,
    "close": 15.75,
    "volume": 5331475,
    "turnover": 83658679,
    "change": 0.35
  },
  {
    "date": "2025-12-23",
    "open": 15.75,
    "high": 15.8,
    "low": 15.5,
    "close": 15.65,
    "volume": 3232031,
    "turnover": 50491331,
    "change": -0.1
  },
  {
    "date": "2025-12-24",
    "open": 15.8,
    "high": 15.85,
    "low": 15.2,
    "close": 15.2,
    "volume": 5340511,
    "turnover": 82307568,
    "change": -0.45
  },
  {
    "date": "2025-12-26",
    "open": 15.15,
    "high": 15.35,
    "low": 15.1,
    "close": 15.15,
    "volume": 2972117,
    "turnover": 45199548,
    "change": -0.05
  },
  {
    "date": "2025-12-29",
    "open": 15.15,
    "high": 15.3,
    "low": 15.15,
    "close": 15.15,
    "volume": 2011003,
    "turnover": 30614345,
    "change": 0.0
  },
  {
    "date": "2025-12-30",
    "open": 15.25,
    "high": 15.35,
    "low": 15.05,
    "close": 15.2,
    "volume": 2048626,
    "turnover": 31153879,
    "change": 0.05
  },
  {
    "date": "2025-12-31",
    "open": 15.2,
    "high": 15.25,
    "low": 14.8,
    "close": 15.0,
    "volume": 4032530,
    "turnover": 60491657,
    "change": -0.2
  }
]